pytrip/__init__.py
pytrip/_cntr.cpython-312-x86_64-linux-gnu.so
pytrip/_version.py
pytrip/ctx.py
pytrip/cube.py
pytrip/ddd.py
pytrip/dicomhelper.py
pytrip/dos.py
pytrip/error.py
pytrip/field.py
pytrip/file_parser.py
pytrip/let.py
pytrip/paths.py
pytrip/pytriplib.cpython-312-x86_64-linux-gnu.so
pytrip/raster.py
pytrip/spc.py
pytrip/util.py
pytrip/vdx.py
pytrip/volhist.py
pytrip/data/OER_barendsen.dat
pytrip/data/OER_furusawa_HSG_C12.dat
pytrip/data/OER_furusawa_V79_C12.dat
pytrip/data/hlut_den.dat
pytrip/lib/cntr.c
pytrip/lib/core.c
pytrip/lib/unused.c
pytrip/models/__init__.py
pytrip/models/extra.py
pytrip/models/proton.py
pytrip/models/rcr.py
pytrip/models/tcp.py
pytrip/res/__init__.py
pytrip/res/contour.py
pytrip/res/interpolate.py
pytrip/res/point.py
pytrip/res/utils.py
pytrip/tripexecuter/__init__.py
pytrip/tripexecuter/execparser.py
pytrip/tripexecuter/execute.py
pytrip/tripexecuter/executor_logger.py
pytrip/tripexecuter/field.py
pytrip/tripexecuter/kernel.py
pytrip/tripexecuter/plan.py
pytrip/tripexecuter/projectile.py
pytrip/utils/__init__.py
pytrip/utils/bevlet2oer.py
pytrip/utils/cubeslice.py
pytrip/utils/dicom2trip.py
pytrip/utils/dvhplot.py
pytrip/utils/gd2agr.py
pytrip/utils/gd2dat.py
pytrip/utils/rst2sobp.py
pytrip/utils/rst_plot.py
pytrip/utils/spc2pdf.py
pytrip/utils/trip2dicom.py
pytrip98-3.11.0.dist-info/METADATA
pytrip98-3.11.0.dist-info/WHEEL
pytrip98-3.11.0.dist-info/entry_points.txt
pytrip98-3.11.0.dist-info/top_level.txt
pytrip98-3.11.0.dist-info/RECORD
pytrip98-3.11.0.dist-info/licenses/LICENSE
