Metadata-Version: 2.4
Name: pytrip98
Version: 3.11.0
Summary: PyTRiP: Python tools for TRiP98 treatment planning and data handling
Author: Jakob Toftegaard, Niels Bassler
Author-email: Leszek Grzanka <leszek.grzanka@ifj.edu.pl>
License-Expression: GPL-3.0-only
Project-URL: Homepage, https://github.com/pytrip/pytrip
Project-URL: Documentation, https://pytrip.readthedocs.io/
Project-URL: Source, https://github.com/pytrip/pytrip
Classifier: Development Status :: 3 - Alpha
Classifier: Intended Audience :: Developers
Classifier: Intended Audience :: Science/Research
Classifier: Topic :: Software Development :: Libraries :: Python Modules
Classifier: Topic :: Scientific/Engineering :: Medical Science Apps.
Classifier: Topic :: Scientific/Engineering :: Physics
Classifier: Environment :: Console
Classifier: Operating System :: POSIX :: Linux
Classifier: Operating System :: Unix
Classifier: Operating System :: Microsoft :: Windows
Classifier: Operating System :: MacOS
Classifier: Programming Language :: C
Classifier: Programming Language :: Python :: 3.9
Classifier: Programming Language :: Python :: 3.10
Classifier: Programming Language :: Python :: 3.11
Classifier: Programming Language :: Python :: 3.12
Classifier: Programming Language :: Python :: 3.13
Classifier: Programming Language :: Python :: 3.14
Classifier: Programming Language :: Python :: Implementation :: CPython
Requires-Python: >=3.9
License-File: LICENSE
Requires-Dist: matplotlib
Requires-Dist: pydicom
Requires-Dist: scipy
Requires-Dist: numpy>=2.0
Provides-Extra: remote
Requires-Dist: paramiko; extra == "remote"
Provides-Extra: test
Requires-Dist: pytest; extra == "test"
Requires-Dist: flake8; extra == "test"
Dynamic: license-file
